dintero/__init__.py
dintero/checkout.py
dintero/error.py
dintero/types.py
dintero/validator.py
dintero/version.py
dintero-0.0.9.dist-info/licenses/LICENSE
dintero-0.0.9.dist-info/METADATA
dintero-0.0.9.dist-info/WHEEL
dintero-0.0.9.dist-info/top_level.txt
dintero-0.0.9.dist-info/RECORD
