Metadata-Version: 2.4
Name: dintero
Version: 0.0.9
Summary: Python bindings for the Dintero API
Home-page: https://github.com/dintero/Dintero.Python.SDK
Author: Dintero
Author-email: integration@dintero.com
License: MIT
Project-URL: Bug Tracker, https://github.com/dintero/Dintero.Python.SDK/issues
Project-URL: Documentation, https://docs.dintero.com
Project-URL: Source Code, https://github.com/dintero/Dintero.Python.SDK
Keywords: dintero api payments
Classifier: Development Status :: 1 - Planning
Classifier: Intended Audience :: Developers
Classifier: License :: OSI Approved :: MIT License
Classifier: Operating System :: OS Independent
Classifier: Programming Language :: Python
Classifier: Programming Language :: Python :: 3
Classifier: Programming Language :: Python :: 3.6
Classifier: Programming Language :: Python :: 3.7
Classifier: Programming Language :: Python :: 3.8
Classifier: Programming Language :: Python :: 3.9
Classifier: Programming Language :: Python :: 3.10
Classifier: Programming Language :: Python :: 3.11
Classifier: Programming Language :: Python :: 3.12
Classifier: Programming Language :: Python :: 3.13
Classifier: Programming Language :: Python :: Implementation :: PyPy
Classifier: Topic :: Software Development :: Libraries :: Python Modules
Requires-Python: >=3.9
License-File: LICENSE
Requires-Dist: requests>=2.20; python_version >= "3.0"
Requires-Dist: typing_extensions>=3.10; python_version >= "3.0"
Provides-Extra: dev
Requires-Dist: pytest; extra == "dev"
Dynamic: author
Dynamic: author-email
Dynamic: classifier
Dynamic: description
Dynamic: description-content-type
Dynamic: home-page
Dynamic: keywords
Dynamic: license
Dynamic: license-file
Dynamic: project-url
Dynamic: provides-extra
Dynamic: requires-dist
Dynamic: requires-python
Dynamic: summary
